pywebdav/__init__.py
pywebdav/__main__.py
pywebdav/__version__.py
pywebdav/lib/AuthServer.py
pywebdav/lib/INI_Parse.py
pywebdav/lib/WebDAVServer.py
pywebdav/lib/__init__.py
pywebdav/lib/constants.py
pywebdav/lib/davcmd.py
pywebdav/lib/davcopy.py
pywebdav/lib/davmove.py
pywebdav/lib/dbconn.py
pywebdav/lib/delete.py
pywebdav/lib/errors.py
pywebdav/lib/iface.py
pywebdav/lib/locks.py
pywebdav/lib/propfind.py
pywebdav/lib/report.py
pywebdav/lib/status.py
pywebdav/lib/utils.py
pywebdav/server/__init__.py
pywebdav/server/daemonize.py
pywebdav/server/fileauth.py
pywebdav/server/fshandler.py
pywebdav/server/mysqlauth.py
pywebdav/server/server.py
PyWebDAV3-0.11.0.dist-info/METADATA
PyWebDAV3-0.11.0.dist-info/WHEEL
PyWebDAV3-0.11.0.dist-info/entry_points.txt
PyWebDAV3-0.11.0.dist-info/top_level.txt
PyWebDAV3-0.11.0.dist-info/RECORD
