Metadata-Version: 2.1
Name: PyWebDAV3
Version: 0.11.0
Summary: WebDAV library including a standalone server for python 3
Home-page: https://github.com/andrewleech/PyWebDAV3
Author: Andrew Leech (previously Simon Pamies)
Author-email: andrew@alelec.net
Maintainer: Andrew Leech (previously Simon Pamies)
Maintainer-email: andrew@alelec.net
License: LGPL v2
Keywords: webdav,server,dav,standalone,library,gpl,http,rfc2518,rfc 2518
Platform: Unix
Platform: Windows
Classifier: Development Status :: 5 - Production/Stable
Classifier: Environment :: Console
Classifier: Environment :: Web Environment
Classifier: Intended Audience :: Developers
Classifier: Intended Audience :: System Administrators
Classifier: License :: OSI Approved :: GNU General Public License (GPL)
Classifier: Operating System :: MacOS :: MacOS X
Classifier: Operating System :: POSIX
Classifier: Programming Language :: Python
Classifier: Topic :: Software Development :: Libraries
Requires-Dist: six
